Metadata-Version: 1.2
Name: t4c-utils
Version: 0.0.2
Summary: T4C utils
Home-page: https://github.com/NewbiZ/t4c_utils
Author: Aurelien Vallee
Author-email: aurelien.vallee@protonmail.com
License: UNKNOWN
Platform: UNKNOWN
Requires-Python: >=3.8
